pyams_app_msc/__init__.py
pyams_app_msc/include.py
pyams_app_msc/interfaces.py
pyams_app_msc/component/__init__.py
pyams_app_msc/component/address/__init__.py
pyams_app_msc/component/address/interfaces.py
pyams_app_msc/component/address/zmi/__init__.py
pyams_app_msc/component/admininfo/__init__.py
pyams_app_msc/component/admininfo/interfaces.py
pyams_app_msc/component/admininfo/zmi/__init__.py
pyams_app_msc/component/banking/__init__.py
pyams_app_msc/component/banking/interfaces.py
pyams_app_msc/component/banking/zmi/__init__.py
pyams_app_msc/component/contact/__init__.py
pyams_app_msc/component/contact/interfaces.py
pyams_app_msc/component/contact/zmi/__init__.py
pyams_app_msc/component/duration/__init__.py
pyams_app_msc/component/duration/interfaces.py
pyams_app_msc/component/duration/schema.py
pyams_app_msc/component/duration/zmi/__init__.py
pyams_app_msc/component/duration/zmi/interfaces.py
pyams_app_msc/component/gallery/__init__.py
pyams_app_msc/component/gallery/zmi/__init__.py
pyams_app_msc/component/gallery/zmi/interfaces.py
pyams_app_msc/component/gallery/zmi/templates/gallery-medias.pt
pyams_app_msc/component/gallery/zmi/templates/gallery-view.pt
pyams_app_msc/component/paragraph/__init__.py
pyams_app_msc/component/paragraph/zmi/__init__.py
pyams_app_msc/component/paragraph/zmi/container.py
pyams_app_msc/doctests/README.rst
pyams_app_msc/feature/__init__.py
pyams_app_msc/feature/booking/__init__.py
pyams_app_msc/feature/booking/container.py
pyams_app_msc/feature/booking/interfaces.py
pyams_app_msc/feature/booking/message.py
pyams_app_msc/feature/booking/reminder.py
pyams_app_msc/feature/booking/task.py
pyams_app_msc/feature/booking/api/__init__.py
pyams_app_msc/feature/booking/api/interfaces.py
pyams_app_msc/feature/booking/api/schema.py
pyams_app_msc/feature/booking/skin/__init__.py
pyams_app_msc/feature/booking/skin/templates/booking-new-header.pt
pyams_app_msc/feature/booking/skin/templates/booking-ok.pt
pyams_app_msc-2.7.2.dist-info/LICENSE
pyams_app_msc-2.7.2.dist-info/METADATA
pyams_app_msc-2.7.2.dist-info/WHEEL
pyams_app_msc-2.7.2.dist-info/entry_points.txt
pyams_app_msc-2.7.2.dist-info/namespace_packages.txt
pyams_app_msc-2.7.2.dist-info/top_level.txt
pyams_app_msc-2.7.2.dist-info/RECORD
