Metadata-Version: 2.1
Name: pyams-app-msc
Version: 2.7.2
Summary: PyAMS application for cinema reservation management
Home-page: https://pyams.readthedocs.io
Author: Thierry Florac
Author-email: tflorac@ulthar.net
License: ZPL
Keywords: Pyramid PyAMS
Classifier: License :: OSI Approved :: Zope Public License
Classifier: Development Status :: 4 - Beta
Classifier: Programming Language :: Python
Classifier: Framework :: Pyramid
Classifier: Topic :: Software Development :: Libraries :: Python Modules
Requires-Python: >=3.7
License-File: LICENSE
Requires-Dist: setuptools
Requires-Dist: colander
Requires-Dist: cornice
Requires-Dist: elasticsearch-dsl
Requires-Dist: fanstatic
Requires-Dist: hypatia
Requires-Dist: persistent
Requires-Dist: pillow
Requires-Dist: pyams-catalog >=2.1.0
Requires-Dist: pyams-content >=2.7.0
Requires-Dist: pyams-content-api >=2.1.0
Requires-Dist: pyams-content-es >=2.2.0
Requires-Dist: pyams-content-themes
Requires-Dist: pyams-file
Requires-Dist: pyams-form >=2.1.0
Requires-Dist: pyams-i18n
Requires-Dist: pyams-layer
Requires-Dist: pyams-mail
Requires-Dist: pyams-pagelet
Requires-Dist: pyams-portal
Requires-Dist: pyams-scheduler >=2.7.0
Requires-Dist: pyams-security >=2.2.1
Requires-Dist: pyams-security-views
Requires-Dist: pyams-sequence
Requires-Dist: pyams-site
Requires-Dist: pyams-skin >=2.2.3
Requires-Dist: pyams-table
Requires-Dist: pyams-utils >=2.3.1
Requires-Dist: pyams-viewlet
Requires-Dist: pyams-workflow
Requires-Dist: pyams-zmi >=2.6.0
Requires-Dist: pyams-zmq
Requires-Dist: pyramid
Requires-Dist: pyramid-mailer
Requires-Dist: reportlab
Requires-Dist: requests
Requires-Dist: transaction
Requires-Dist: ZODB
Requires-Dist: zope.annotation
Requires-Dist: zope.container
Requires-Dist: zope.copy
Requires-Dist: zope.dublincore
Requires-Dist: zope.interface
Requires-Dist: zope.intid
Requires-Dist: zope.lifecycleevent
Requires-Dist: zope.location
Requires-Dist: zope.principalannotation
Requires-Dist: zope.schema
Requires-Dist: zope.traversing
Requires-Dist: importlib-resources ; python_version < "3.9"
Provides-Extra: test
Requires-Dist: pyramid-zcml ; extra == 'test'
Requires-Dist: zope.exceptions ; extra == 'test'
